{
	"start_at": 1530165296,
	"words_list": [
		{
			"word": "harm",
			"level": 1,
			"page": 74,
			"sentence": "The kind of packing material will not do harm to people."
		},
		{
			"word": "hat",
			"level": 1,
			"page": 74,
			"sentence": "The strange office clerk always wears a hat."
		},
		{
			"word": "hate",
			"level": 1,
			"page": 74,
			"sentence": "Majority of the employees hate working extra time on holidays."
		},
		{
			"word": "have",
			"level": 1,
			"page": 74,
			"sentence": "The manager invited the cooperator to have dinner in a western restaurant."
		},
		{
			"word": "head",
			"level": 1,
			"page": 74,
			"sentence": "I feel an ache in my head and want a sick leave."
		},
		{
			"word": "health",
			"level": 1,
			"page": 74,
			"sentence": "The sales manager keeps exercising every day in order to be in good health."
		},
		{
			"word": "hear",
			"level": 1,
			"page": 74,
			"sentence": "I heard that Linda would be the new department manager."
		},
		{
			"word": "heat",
			"level": 1,
			"page": 75,
			"sentence": "As far as I know, this imported heat exchanger is very expensive."
		},
		{
			"word": "heavy",
			"level": 1,
			"page": 75,
			"sentence": "The workers looked very tired after carrying these heavy devices."
		},
		{
			"word": "heel",
			"level": 1,
			"page": 75,
			"sentence": "The assistant couldn't catch up with the client with her high heels."
		},
		{
			"word": "help",
			"level": 1,
			"page": 75,
			"sentence": "The waiter could help you carry your luggage to the room."
		},
		{
			"word": "here",
			"level": 1,
			"page": 75,
			"sentence": "He remained waiting for the applicant here for two hours."
		},
		{
			"word": "high",
			"level": 1,
			"page": 75,
			"sentence": "He drove the car at high speed in order to arrive at the airport on time."
		},
		{
			"word": "lean",
			"level": 2,
			"page": 202,
			"sentence": "The respectable old worker is so tired that he leaned against the wall."
		},
		{
			"word": "lease",
			"level": 2,
			"page": 202,
			"sentence": "I have to tell you that the lease on this office is overdue."
		},
		{
			"word": "lecture",
			"level": 2,
			"page": 202,
			"sentence": "The credible speaker gave a public lecture at the press conference."
		},
		{
			"word": "legal",
			"level": 2,
			"page": 202,
			"sentence": "The manager decided to engage the young man as a legal adviser."
		},
		{
			"word": "limit",
			"level": 2,
			"page": 202,
			"sentence": "The only remaining question is whether the boss will set a limit to the expense of business trips."
		},
		{
			"word": "load",
			"level": 2,
			"page": 202,
			"sentence": "This good news took a load off the boss's mind."
		},
		{
			"word": "loan",
			"level": 2,
			"page": 202,
			"sentence": "The bank agreed to make a loan for one hundred thousand dollars to them."
		},
		{
			"word": "locate",
			"level": 2,
			"page": 203,
			"sentence": "The new office building is located in the Third Avenue."
		},
		{
			"word": "lodge",
			"level": 2,
			"page": 203,
			"sentence": "This new employee who went to hospital yesterday lodged in his friend's home."
		},
		{
			"word": "logo",
			"level": 2,
			"page": 203,
			"sentence": "The customers want to buy glasses bearing this logo."
		},
		{
			"word": "loss",
			"level": 2,
			"page": 203,
			"sentence": "The failure of negotiation was a great loss the company."
		},
		{
			"word": "luggage",
			"level": 2,
			"page": 203,
			"sentence": "Could you help me carry my luggage to the guest room?"
		},
		{
			"word": "margin",
			"level": 3,
			"page": 304,
			"sentence": "The information on the margin of the report is particularly important."
		},
		{
			"word": "massive",
			"level": 3,
			"page": 304,
			"sentence": "You must make massive efforts to finish the task on time."
		},
		{
			"word": "maximum",
			"level": 3,
			"page": 304,
			"sentence": "The conference room can hold a maximum of two hundred people."
		},
		{
			"word": "melt",
			"level": 3,
			"page": 304,
			"sentence": "The travelers left the scenic spot after the snow began to melt."
		},
		{
			"word": "memorize",
			"level": 3,
			"page": 304,
			"sentence": "The boss asked us to memorize these rules."
		},
		{
			"word": "merchant",
			"level": 3,
			"page": 304,
			"sentence": "The merchant was accused of escaping taxation."
		},
		{
			"word": "merge",
			"level": 3,
			"page": 304,
			"sentence": "The only way is to merge your company with the big enterprise."
		},
		{
			"word": "merger",
			"level": 3,
			"page": 305,
			"sentence": "All of the employees are talking about the impending merger of the two companies."
		},
		{
			"word": "metro",
			"level": 3,
			"page": 305,
			"sentence": "Most of my colleagues go to work by metro."
		},
		{
			"word": "micro",
			"level": 3,
			"page": 305,
			"sentence": "The boss told him to buy a micro computer as soon as possible."
		},
		{
			"word": "midst",
			"level": 3,
			"page": 305,
			"sentence": "The travelers have walked in the midst of the heavy rain for about half an hour."
		},
		{
			"word": "mingle",
			"level": 3,
			"page": 305,
			"sentence": "The expert warned his assistant not to mingle water and alcohol."
		},
		{
			"word": "minimal",
			"level": 3,
			"page": 305,
			"sentence": "For example, the expenses of the employees in the marketing department are minimal."
		},
		{
			"word": "ministry",
			"level": 3,
			"page": 305,
			"sentence": "Some officials in the ministry of finance often sit idly in the work time."
		},
		{
			"word": "levy",
			"level": 4,
			"page": 402,
			"sentence": "Has the government imposed a levy on foreign imports?"
		},
		{
			"word": "liability",
			"level": 4,
			"page": 402,
			"sentence": "The shipping company doesn't admit liability for the damage caused by the storm."
		},
		{
			"word": "liaison",
			"level": 4,
			"page": 402,
			"sentence": "The manager praised the excellent liaison between the two departments."
		},
		{
			"word": "liberty",
			"level": 4,
			"page": 402,
			"sentence": "All the employees are at liberty to express their own opinions."
		},
		{
			"word": "librarian",
			"level": 4,
			"page": 402,
			"sentence": "The librarian goes to work by bus every day."
		},
		{
			"word": "lifelong",
			"level": 4,
			"page": 402,
			"sentence": "The policy puts an end to the lifelong employment system."
		},
		{
			"word": "lifetime",
			"level": 4,
			"page": 403,
			"sentence": "The position offered the chance of a lifetime to her."
		},
		{
			"word": "lightweight",
			"level": 4,
			"page": 403,
			"sentence": "The manager considered him to be lightweight for the program."
		},
		{
			"word": "likelihood",
			"level": 4,
			"page": 403,
			"sentence": "There is very little likelihood that she will get the position."
		},
		{
			"word": "likewise",
			"level": 4,
			"page": 403,
			"sentence": "Actually, her second job waslikewise well-paid."
		},
		{
			"word": "limitation",
			"level": 4,
			"page": 403,
			"sentence": "The young cleark refused to admit his limitations."
		},
		{
			"word": "live-in",
			"level": 4,
			"page": 403,
			"sentence": "They employed a live-in nanny for the baby."
		},
		{
			"word": "livestock",
			"level": 4,
			"page": 403,
			"sentence": "I'm afraid the heavy storm will have an effect on the livestock."
		},
		{
			"word": "impenetrable",
			"level": 5,
			"page": 506,
			"sentence": "The theory seemed to be impenetrable to her."
		},
		{
			"word": "implementation",
			"level": 5,
			"page": 506,
			"sentence": "I wonder if you have any question about the loan implementation."
		},
		{
			"word": "imposing",
			"level": 5,
			"page": 506,
			"sentence": "That is why we come to the imposing gymnasium."
		},
		{
			"word": "impotent",
			"level": 5,
			"page": 506,
			"sentence": "I'm afraid she will be impotent without the director's support."
		},
		{
			"word": "incentive",
			"level": 5,
			"page": 506,
			"sentence": "The idea came to his mind that bonus payments may be an incentive to work hard."
		},
		{
			"word": "incinerate",
			"level": 5,
			"page": 506,
			"sentence": "Most of the waste had been incinerated yesterday."
		},
		{
			"word": "incinerator",
			"level": 5,
			"page": 507,
			"sentence": "The man gave the order that the garbage incinerator should be built in a week."
		},
		{
			"word": "incoherent",
			"level": 5,
			"page": 507,
			"sentence": "The director is not satisfied with his incoherent explanation."
		},
		{
			"word": "incompetent",
			"level": 5,
			"page": 507,
			"sentence": "There has been violent opposition to the incompetent manager."
		},
		{
			"word": "incredibility",
			"level": 5,
			"page": 507,
			"sentence": "We have no idea whether we should point out the incredibility of her story."
		},
		{
			"word": "incumbent",
			"level": 5,
			"page": 507,
			"sentence": "It's incumbent on them to pay the rent."
		},
		{
			"word": "incur",
			"level": 5,
			"page": 507,
			"sentence": "We wondered if the proposal will incur the manager's displeasure."
		}
	]
}